automate_LinearRegression/__init__.py
automate_LinearRegression/automate.py
automate_LinearRegression-1.0.1.dist-info/LICENSE
automate_LinearRegression-1.0.1.dist-info/METADATA
automate_LinearRegression-1.0.1.dist-info/WHEEL
automate_LinearRegression-1.0.1.dist-info/top_level.txt
automate_LinearRegression-1.0.1.dist-info/RECORD
