Metadata-Version: 2.1
Name: automate-LinearRegression
Version: 1.0.1
Summary: Linear-Regression-Automation
Author: Suryansh
Author-email: <suryanshgrover1999@gmail.com>
Keywords: python,machine learning,machine learning model,regression,linear regression,lasso linear regression,elasticnet linear regression,regularization
Classifier: Development Status :: 1 - Planning
Classifier: Intended Audience :: Developers
Classifier: Programming Language :: Python :: 3
Classifier: Operating System :: Microsoft :: Windows
Classifier: Operating System :: MacOS :: MacOS X
License-File: LICENSE
Requires-Dist: scikit-learn
Requires-Dist: numpy
